.gitignore
.travis.yml
HISTORY.rst
LICENSE
README.md
setup.py
.github/issue_template.md
.github/workflows/publish.yaml
requirements/base.txt
requirements/tests.txt
se_dns/__init__.py
se_dns/combined_lists.json
se_dns/dnsutil.py
se_dns.egg-info/PKG-INFO
se_dns.egg-info/SOURCES.txt
se_dns.egg-info/dependency_links.txt
se_dns.egg-info/requires.txt
se_dns.egg-info/top_level.txt
tests/__init__.py
tests/functional/__init__.py
tests/unit/__init__.py
tests/unit/test_dnsutil.py
tests/util/__init__.py