Metadata-Version: 1.1
Name: se-dns
Version: 0.1
Summary: Simple dns tools.
Home-page: UNKNOWN
Author: SpamExperts
Author-email: UNKNOWN
License: GPL
Keywords: server
Platform: POSIX
Classifier: Operating System :: POSIX
Classifier: Programming Language :: Python
Classifier: Intended Audience :: System Administrators
Classifier: Development Status :: 5 - Production/Stable
Classifier: License :: OSI Approved :: GNU General Public License v2 (GPLv2)
